fflgs/__init__.py
fflgs/_version.py
fflgs/core.py
fflgs/py.typed
fflgs/cache/__init__.py
fflgs/cache/_cache.py
fflgs/cache/_utils.py
fflgs/cache/memory.py
fflgs/cache/protocol.py
fflgs/providers/__init__.py
fflgs/providers/_file_provider.py
fflgs/providers/_utils.py
fflgs/providers/json.py
fflgs/providers/memory.py
fflgs/providers/protocol.py
fflgs/providers/yaml.py
fflgs-0.0.0a2.dist-info/METADATA
fflgs-0.0.0a2.dist-info/WHEEL
fflgs-0.0.0a2.dist-info/licenses/AUTHORS.md
fflgs-0.0.0a2.dist-info/licenses/LICENSE.txt
fflgs-0.0.0a2.dist-info/RECORD
