Metadata-Version: 2.4
Name: fflgs
Version: 0.0.0a2
Summary: Feature flags
Project-URL: Documentation, https://github.com/bartosz121/fflgs
Project-URL: Source, https://github.com/bartosz121/fflgs
Project-URL: Tracker, https://github.com/bartosz121/fflgs/issues
Author-email: Bartosz Magiera <admin@bartoszmagiera.dev>
License: MIT
License-File: AUTHORS.md
License-File: LICENSE.txt
Keywords: feature-flags
Classifier: Development Status :: 2 - Pre-Alpha
Classifier: Programming Language :: Python
Classifier: Programming Language :: Python :: 3.10
Classifier: Programming Language :: Python :: 3.11
Classifier: Programming Language :: Python :: 3.12
Classifier: Programming Language :: Python :: 3.13
Classifier: Programming Language :: Python :: 3.14
Classifier: Programming Language :: Python :: Implementation :: CPython
Requires-Python: >=3.10
Provides-Extra: yaml
Requires-Dist: pyyaml<7,>=6; extra == 'yaml'
